ApplePayBianchengZhinan/README.md
ApplePayBianchengZhinan/__init__.py
ApplePayBianchengZhinan/__main__.py
ApplePayBianchengZhinan/file.epub
ApplePayBianchengZhinan/index.html
ApplePayBianchengZhinan/css/__init__.py
ApplePayBianchengZhinan/css/annotations.css
ApplePayBianchengZhinan/css/main.css
ApplePayBianchengZhinan/css/normalize.css
ApplePayBianchengZhinan/css/popup.css
ApplePayBianchengZhinan/font/__init__.py
ApplePayBianchengZhinan/font/fontello.eot
ApplePayBianchengZhinan/font/fontello.svg
ApplePayBianchengZhinan/font/fontello.ttf
ApplePayBianchengZhinan/font/fontello.woff
ApplePayBianchengZhinan/img/__init__.py
ApplePayBianchengZhinan/img/annotator-glyph-sprite.png
ApplePayBianchengZhinan/img/annotator-icon-sprite.png
ApplePayBianchengZhinan/img/apple-touch-icon.png
ApplePayBianchengZhinan/img/cancelfullscreen.png
ApplePayBianchengZhinan/img/close.png
ApplePayBianchengZhinan/img/fullscreen.png
ApplePayBianchengZhinan/img/loader.gif
ApplePayBianchengZhinan/img/menu-icon.png
ApplePayBianchengZhinan/img/save.png
ApplePayBianchengZhinan/img/saved.png
ApplePayBianchengZhinan/img/settings-s.png
ApplePayBianchengZhinan/img/settings.png
ApplePayBianchengZhinan/img/star.png
ApplePayBianchengZhinan/js/__init__.py
ApplePayBianchengZhinan/js/epub.js
ApplePayBianchengZhinan/js/epub.min.js
ApplePayBianchengZhinan/js/epub.min.map
ApplePayBianchengZhinan/js/hooks.min.js
ApplePayBianchengZhinan/js/hooks.min.map
ApplePayBianchengZhinan/js/reader.js
ApplePayBianchengZhinan/js/reader.js.map
ApplePayBianchengZhinan/js/reader.min.js
ApplePayBianchengZhinan/js/reader.min.map
ApplePayBianchengZhinan/js/hooks/__init__.py
ApplePayBianchengZhinan/js/hooks/extensions/__init__.py
ApplePayBianchengZhinan/js/hooks/extensions/highlight.js
ApplePayBianchengZhinan/js/libs/__init__.py
ApplePayBianchengZhinan/js/libs/jquery.min.js
ApplePayBianchengZhinan/js/libs/localforage.min.js
ApplePayBianchengZhinan/js/libs/screenfull.js
ApplePayBianchengZhinan/js/libs/screenfull.min.js
apple_pay_biancheng_zhinan-2024.3.3.0.dist-info/METADATA
apple_pay_biancheng_zhinan-2024.3.3.0.dist-info/WHEEL
apple_pay_biancheng_zhinan-2024.3.3.0.dist-info/entry_points.txt
apple_pay_biancheng_zhinan-2024.3.3.0.dist-info/top_level.txt
apple_pay_biancheng_zhinan-2024.3.3.0.dist-info/RECORD
